itemset_mining/VERSION
itemset_mining/__init__.py
itemset_mining/two_phase_huim.py
itemset_mining-0.2.2.dist-info/LICENSE
itemset_mining-0.2.2.dist-info/METADATA
itemset_mining-0.2.2.dist-info/WHEEL
itemset_mining-0.2.2.dist-info/top_level.txt
itemset_mining-0.2.2.dist-info/RECORD
