Metadata-Version: 2.1
Name: itemset-mining
Version: 0.2.2
Summary: A python package for itemset mining algorithms.
Home-page: https://github.com/zaxr/itemset_mining
Author: Zax Rosenberg
Author-email: zaxr@protonmail.com
License: UNKNOWN
Keywords: high utility itemset mining data pattern huim apriori frequent
Platform: UNKNOWN
Classifier: Development Status :: 3 - Alpha
Classifier: Intended Audience :: Developers
Classifier: License :: OSI Approved :: GNU Lesser General Public License v3 (LGPLv3)
Classifier: Natural Language :: English
Classifier: Programming Language :: Python :: 3
Classifier: Programming Language :: Python :: 3.6
Classifier: Programming Language :: Python :: 3.7
Classifier: Programming Language :: Python :: 3.8
Classifier: Programming Language :: Python :: 3.9
Requires-Python: >=3.6
License-File: LICENSE
Provides-Extra: dev
Requires-Dist: pytest ; extra == 'dev'
Requires-Dist: pytest-cases ; extra == 'dev'
Requires-Dist: pytest-cov ; extra == 'dev'
Requires-Dist: Jinja2 (<3.1) ; extra == 'dev'
Requires-Dist: mistune (~=0.8.4) ; extra == 'dev'
Requires-Dist: m2r ; extra == 'dev'
Requires-Dist: setuptools (>=30.4) ; extra == 'dev'
Requires-Dist: Sphinx (~=2.0) ; extra == 'dev'
Requires-Dist: sphinxcontrib-apidoc (~=0.3.0) ; extra == 'dev'
Requires-Dist: sphinx-rtd-theme ; extra == 'dev'
Requires-Dist: pre-commit ; extra == 'dev'
Requires-Dist: tox ; extra == 'dev'
Provides-Extra: docs
Requires-Dist: Jinja2 (<3.1) ; extra == 'docs'
Requires-Dist: mistune (~=0.8.4) ; extra == 'docs'
Requires-Dist: m2r ; extra == 'docs'
Requires-Dist: setuptools (>=30.4) ; extra == 'docs'
Requires-Dist: Sphinx (~=2.0) ; extra == 'docs'
Requires-Dist: sphinxcontrib-apidoc (~=0.3.0) ; extra == 'docs'
Requires-Dist: sphinx-rtd-theme ; extra == 'docs'
Provides-Extra: test
Requires-Dist: pytest ; extra == 'test'
Requires-Dist: pytest-cases ; extra == 'test'
Requires-Dist: pytest-cov ; extra == 'test'
